{
  "openapi": "3.0.1",
  "info": {
    "title": "ORBITA Career API",
    "description": "API do projeto ORBITA – Laboratório de Carreiras do Futuro (Global Solution – Futuro do Trabalho)",
    "version": "v1"
  },
  "paths": {
    "/api/v{version}/CareerPaths": {
      "get": {
        "tags": [
          "CareerPaths"
        ],
        "parameters": [
          {
            "name": "version",
            "in": "path",
            "required": true,
            "schema": {
              "type": "string"
            }
          }
        ],
        "responses": {
          "200": {
            "description": "Success",
            "content": {
              "text/plain": {
                "schema": {
                  "type": "array",
                  "items": {
                    "$ref": "#/components/schemas/CareerPath"
                  }
                }
              },
              "application/json": {
                "schema": {
                  "type": "array",
                  "items": {
                    "$ref": "#/components/schemas/CareerPath"
                  }
                }
              },
              "text/json": {
                "schema": {
                  "type": "array",
                  "items": {
                    "$ref": "#/components/schemas/CareerPath"
                  }
                }
              }
            }
          }
        }
      },
      "post": {
        "tags": [
          "CareerPaths"
        ],
        "parameters": [
          {
            "name": "version",
            "in": "path",
            "required": true,
            "schema": {
              "type": "string"
            }
          }
        ],
        "requestBody": {
          "content": {
            "application/json": {
              "schema": {
                "$ref": "#/components/schemas/CareerPath"
              }
            },
            "text/json": {
              "schema": {
                "$ref": "#/components/schemas/CareerPath"
              }
            },
            "application/*+json": {
              "schema": {
                "$ref": "#/components/schemas/CareerPath"
              }
            }
          }
        },
        "responses": {
          "200": {
            "description": "Success",
            "content": {
              "text/plain": {
                "schema": {
                  "$ref": "#/components/schemas/CareerPath"
                }
              },
              "application/json": {
                "schema": {
                  "$ref": "#/components/schemas/CareerPath"
                }
              },
              "text/json": {
                "schema": {
                  "$ref": "#/components/schemas/CareerPath"
                }
              }
            }
          }
        }
      }
    },
    "/api/v{version}/CareerPaths/{id}": {
      "get": {
        "tags": [
          "CareerPaths"
        ],
        "parameters": [
          {
            "name": "id",
            "in": "path",
            "required": true,
            "schema": {
              "type": "string",
              "format": "uuid"
            }
          },
          {
            "name": "version",
            "in": "path",
            "required": true,
            "schema": {
              "type": "string"
            }
          }
        ],
        "responses": {
          "200": {
            "description": "Success",
            "content": {
              "text/plain": {
                "schema": {
                  "$ref": "#/components/schemas/CareerPath"
                }
              },
              "application/json": {
                "schema": {
                  "$ref": "#/components/schemas/CareerPath"
                }
              },
              "text/json": {
                "schema": {
                  "$ref": "#/components/schemas/CareerPath"
                }
              }
            }
          }
        }
      },
      "put": {
        "tags": [
          "CareerPaths"
        ],
        "parameters": [
          {
            "name": "id",
            "in": "path",
            "required": true,
            "schema": {
              "type": "string",
              "format": "uuid"
            }
          },
          {
            "name": "version",
            "in": "path",
            "required": true,
            "schema": {
              "type": "string"
            }
          }
        ],
        "requestBody": {
          "content": {
            "application/json": {
              "schema": {
                "$ref": "#/components/schemas/CareerPath"
              }
            },
            "text/json": {
              "schema": {
                "$ref": "#/components/schemas/CareerPath"
              }
            },
            "application/*+json": {
              "schema": {
                "$ref": "#/components/schemas/CareerPath"
              }
            }
          }
        },
        "responses": {
          "200": {
            "description": "Success"
          }
        }
      },
      "delete": {
        "tags": [
          "CareerPaths"
        ],
        "parameters": [
          {
            "name": "id",
            "in": "path",
            "required": true,
            "schema": {
              "type": "string",
              "format": "uuid"
            }
          },
          {
            "name": "version",
            "in": "path",
            "required": true,
            "schema": {
              "type": "string"
            }
          }
        ],
        "responses": {
          "200": {
            "description": "Success"
          }
        }
      }
    },
    "/api/v{version}/CareerPaths/{id}/missions": {
      "get": {
        "tags": [
          "CareerPaths"
        ],
        "parameters": [
          {
            "name": "id",
            "in": "path",
            "required": true,
            "schema": {
              "type": "string",
              "format": "uuid"
            }
          },
          {
            "name": "version",
            "in": "path",
            "required": true,
            "schema": {
              "type": "string"
            }
          }
        ],
        "responses": {
          "200": {
            "description": "Success",
            "content": {
              "text/plain": {
                "schema": {
                  "type": "array",
                  "items": {
                    "$ref": "#/components/schemas/Mission"
                  }
                }
              },
              "application/json": {
                "schema": {
                  "type": "array",
                  "items": {
                    "$ref": "#/components/schemas/Mission"
                  }
                }
              },
              "text/json": {
                "schema": {
                  "type": "array",
                  "items": {
                    "$ref": "#/components/schemas/Mission"
                  }
                }
              }
            }
          }
        }
      }
    },
    "/api/v{version}/CareerPathsV": {
      "get": {
        "tags": [
          "CareerPathsV"
        ],
        "parameters": [
          {
            "name": "version",
            "in": "path",
            "required": true,
            "schema": {
              "type": "string"
            }
          }
        ],
        "responses": {
          "200": {
            "description": "Success"
          }
        }
      }
    },
    "/api/v{version}/Missions": {
      "get": {
        "tags": [
          "Missions"
        ],
        "parameters": [
          {
            "name": "careerPathId",
            "in": "query",
            "schema": {
              "type": "string",
              "format": "uuid"
            }
          },
          {
            "name": "version",
            "in": "path",
            "required": true,
            "schema": {
              "type": "string"
            }
          }
        ],
        "responses": {
          "200": {
            "description": "Success",
            "content": {
              "text/plain": {
                "schema": {
                  "type": "array",
                  "items": {
                    "$ref": "#/components/schemas/Mission"
                  }
                }
              },
              "application/json": {
                "schema": {
                  "type": "array",
                  "items": {
                    "$ref": "#/components/schemas/Mission"
                  }
                }
              },
              "text/json": {
                "schema": {
                  "type": "array",
                  "items": {
                    "$ref": "#/components/schemas/Mission"
                  }
                }
              }
            }
          }
        }
      },
      "post": {
        "tags": [
          "Missions"
        ],
        "parameters": [
          {
            "name": "version",
            "in": "path",
            "required": true,
            "schema": {
              "type": "string"
            }
          }
        ],
        "requestBody": {
          "content": {
            "application/json": {
              "schema": {
                "$ref": "#/components/schemas/Mission"
              }
            },
            "text/json": {
              "schema": {
                "$ref": "#/components/schemas/Mission"
              }
            },
            "application/*+json": {
              "schema": {
                "$ref": "#/components/schemas/Mission"
              }
            }
          }
        },
        "responses": {
          "200": {
            "description": "Success",
            "content": {
              "text/plain": {
                "schema": {
                  "$ref": "#/components/schemas/Mission"
                }
              },
              "application/json": {
                "schema": {
                  "$ref": "#/components/schemas/Mission"
                }
              },
              "text/json": {
                "schema": {
                  "$ref": "#/components/schemas/Mission"
                }
              }
            }
          }
        }
      }
    },
    "/api/v{version}/Missions/{id}": {
      "get": {
        "tags": [
          "Missions"
        ],
        "parameters": [
          {
            "name": "id",
            "in": "path",
            "required": true,
            "schema": {
              "type": "string",
              "format": "uuid"
            }
          },
          {
            "name": "version",
            "in": "path",
            "required": true,
            "schema": {
              "type": "string"
            }
          }
        ],
        "responses": {
          "200": {
            "description": "Success",
            "content": {
              "text/plain": {
                "schema": {
                  "$ref": "#/components/schemas/Mission"
                }
              },
              "application/json": {
                "schema": {
                  "$ref": "#/components/schemas/Mission"
                }
              },
              "text/json": {
                "schema": {
                  "$ref": "#/components/schemas/Mission"
                }
              }
            }
          }
        }
      },
      "put": {
        "tags": [
          "Missions"
        ],
        "parameters": [
          {
            "name": "id",
            "in": "path",
            "required": true,
            "schema": {
              "type": "string",
              "format": "uuid"
            }
          },
          {
            "name": "version",
            "in": "path",
            "required": true,
            "schema": {
              "type": "string"
            }
          }
        ],
        "requestBody": {
          "content": {
            "application/json": {
              "schema": {
                "$ref": "#/components/schemas/Mission"
              }
            },
            "text/json": {
              "schema": {
                "$ref": "#/components/schemas/Mission"
              }
            },
            "application/*+json": {
              "schema": {
                "$ref": "#/components/schemas/Mission"
              }
            }
          }
        },
        "responses": {
          "200": {
            "description": "Success"
          }
        }
      },
      "delete": {
        "tags": [
          "Missions"
        ],
        "parameters": [
          {
            "name": "id",
            "in": "path",
            "required": true,
            "schema": {
              "type": "string",
              "format": "uuid"
            }
          },
          {
            "name": "version",
            "in": "path",
            "required": true,
            "schema": {
              "type": "string"
            }
          }
        ],
        "responses": {
          "200": {
            "description": "Success"
          }
        }
      }
    },
    "/api/v{version}/Progress": {
      "get": {
        "tags": [
          "Progress"
        ],
        "parameters": [
          {
            "name": "userId",
            "in": "query",
            "schema": {
              "type": "string",
              "format": "uuid"
            }
          },
          {
            "name": "version",
            "in": "path",
            "required": true,
            "schema": {
              "type": "string"
            }
          }
        ],
        "responses": {
          "200": {
            "description": "Success",
            "content": {
              "text/plain": {
                "schema": {
                  "type": "array",
                  "items": {
                    "$ref": "#/components/schemas/UserMissionProgress"
                  }
                }
              },
              "application/json": {
                "schema": {
                  "type": "array",
                  "items": {
                    "$ref": "#/components/schemas/UserMissionProgress"
                  }
                }
              },
              "text/json": {
                "schema": {
                  "type": "array",
                  "items": {
                    "$ref": "#/components/schemas/UserMissionProgress"
                  }
                }
              }
            }
          }
        }
      },
      "post": {
        "tags": [
          "Progress"
        ],
        "parameters": [
          {
            "name": "version",
            "in": "path",
            "required": true,
            "schema": {
              "type": "string"
            }
          }
        ],
        "requestBody": {
          "content": {
            "application/json": {
              "schema": {
                "$ref": "#/components/schemas/UserMissionProgress"
              }
            },
            "text/json": {
              "schema": {
                "$ref": "#/components/schemas/UserMissionProgress"
              }
            },
            "application/*+json": {
              "schema": {
                "$ref": "#/components/schemas/UserMissionProgress"
              }
            }
          }
        },
        "responses": {
          "200": {
            "description": "Success",
            "content": {
              "text/plain": {
                "schema": {
                  "$ref": "#/components/schemas/UserMissionProgress"
                }
              },
              "application/json": {
                "schema": {
                  "$ref": "#/components/schemas/UserMissionProgress"
                }
              },
              "text/json": {
                "schema": {
                  "$ref": "#/components/schemas/UserMissionProgress"
                }
              }
            }
          }
        }
      }
    },
    "/api/v{version}/Progress/{id}": {
      "get": {
        "tags": [
          "Progress"
        ],
        "parameters": [
          {
            "name": "id",
            "in": "path",
            "required": true,
            "schema": {
              "type": "string",
              "format": "uuid"
            }
          },
          {
            "name": "version",
            "in": "path",
            "required": true,
            "schema": {
              "type": "string"
            }
          }
        ],
        "responses": {
          "200": {
            "description": "Success",
            "content": {
              "text/plain": {
                "schema": {
                  "$ref": "#/components/schemas/UserMissionProgress"
                }
              },
              "application/json": {
                "schema": {
                  "$ref": "#/components/schemas/UserMissionProgress"
                }
              },
              "text/json": {
                "schema": {
                  "$ref": "#/components/schemas/UserMissionProgress"
                }
              }
            }
          }
        }
      },
      "put": {
        "tags": [
          "Progress"
        ],
        "parameters": [
          {
            "name": "id",
            "in": "path",
            "required": true,
            "schema": {
              "type": "string",
              "format": "uuid"
            }
          },
          {
            "name": "version",
            "in": "path",
            "required": true,
            "schema": {
              "type": "string"
            }
          }
        ],
        "requestBody": {
          "content": {
            "application/json": {
              "schema": {
                "$ref": "#/components/schemas/UserMissionProgress"
              }
            },
            "text/json": {
              "schema": {
                "$ref": "#/components/schemas/UserMissionProgress"
              }
            },
            "application/*+json": {
              "schema": {
                "$ref": "#/components/schemas/UserMissionProgress"
              }
            }
          }
        },
        "responses": {
          "200": {
            "description": "Success"
          }
        }
      },
      "delete": {
        "tags": [
          "Progress"
        ],
        "parameters": [
          {
            "name": "id",
            "in": "path",
            "required": true,
            "schema": {
              "type": "string",
              "format": "uuid"
            }
          },
          {
            "name": "version",
            "in": "path",
            "required": true,
            "schema": {
              "type": "string"
            }
          }
        ],
        "responses": {
          "200": {
            "description": "Success"
          }
        }
      }
    },
    "/api/v{version}/Users": {
      "get": {
        "tags": [
          "Users"
        ],
        "parameters": [
          {
            "name": "version",
            "in": "path",
            "required": true,
            "schema": {
              "type": "string"
            }
          }
        ],
        "responses": {
          "200": {
            "description": "Success",
            "content": {
              "text/plain": {
                "schema": {
                  "type": "array",
                  "items": {
                    "$ref": "#/components/schemas/User"
                  }
                }
              },
              "application/json": {
                "schema": {
                  "type": "array",
                  "items": {
                    "$ref": "#/components/schemas/User"
                  }
                }
              },
              "text/json": {
                "schema": {
                  "type": "array",
                  "items": {
                    "$ref": "#/components/schemas/User"
                  }
                }
              }
            }
          }
        }
      },
      "post": {
        "tags": [
          "Users"
        ],
        "parameters": [
          {
            "name": "version",
            "in": "path",
            "required": true,
            "schema": {
              "type": "string"
            }
          }
        ],
        "requestBody": {
          "content": {
            "application/json": {
              "schema": {
                "$ref": "#/components/schemas/User"
              }
            },
            "text/json": {
              "schema": {
                "$ref": "#/components/schemas/User"
              }
            },
            "application/*+json": {
              "schema": {
                "$ref": "#/components/schemas/User"
              }
            }
          }
        },
        "responses": {
          "200": {
            "description": "Success",
            "content": {
              "text/plain": {
                "schema": {
                  "$ref": "#/components/schemas/User"
                }
              },
              "application/json": {
                "schema": {
                  "$ref": "#/components/schemas/User"
                }
              },
              "text/json": {
                "schema": {
                  "$ref": "#/components/schemas/User"
                }
              }
            }
          }
        }
      }
    },
    "/api/v{version}/Users/{id}": {
      "get": {
        "tags": [
          "Users"
        ],
        "parameters": [
          {
            "name": "id",
            "in": "path",
            "required": true,
            "schema": {
              "type": "string",
              "format": "uuid"
            }
          },
          {
            "name": "version",
            "in": "path",
            "required": true,
            "schema": {
              "type": "string"
            }
          }
        ],
        "responses": {
          "200": {
            "description": "Success",
            "content": {
              "text/plain": {
                "schema": {
                  "$ref": "#/components/schemas/User"
                }
              },
              "application/json": {
                "schema": {
                  "$ref": "#/components/schemas/User"
                }
              },
              "text/json": {
                "schema": {
                  "$ref": "#/components/schemas/User"
                }
              }
            }
          }
        }
      },
      "put": {
        "tags": [
          "Users"
        ],
        "parameters": [
          {
            "name": "id",
            "in": "path",
            "required": true,
            "schema": {
              "type": "string",
              "format": "uuid"
            }
          },
          {
            "name": "version",
            "in": "path",
            "required": true,
            "schema": {
              "type": "string"
            }
          }
        ],
        "requestBody": {
          "content": {
            "application/json": {
              "schema": {
                "$ref": "#/components/schemas/User"
              }
            },
            "text/json": {
              "schema": {
                "$ref": "#/components/schemas/User"
              }
            },
            "application/*+json": {
              "schema": {
                "$ref": "#/components/schemas/User"
              }
            }
          }
        },
        "responses": {
          "200": {
            "description": "Success"
          }
        }
      },
      "delete": {
        "tags": [
          "Users"
        ],
        "parameters": [
          {
            "name": "id",
            "in": "path",
            "required": true,
            "schema": {
              "type": "string",
              "format": "uuid"
            }
          },
          {
            "name": "version",
            "in": "path",
            "required": true,
            "schema": {
              "type": "string"
            }
          }
        ],
        "responses": {
          "200": {
            "description": "Success"
          }
        }
      }
    }
  },
  "components": {
    "schemas": {
      "CareerPath": {
        "type": "object",
        "properties": {
          "id": {
            "type": "string",
            "format": "uuid"
          },
          "name": {
            "type": "string",
            "nullable": true
          },
          "area": {
            "type": "string",
            "nullable": true
          },
          "description": {
            "type": "string",
            "nullable": true
          },
          "level": {
            "type": "string",
            "nullable": true
          },
          "missions": {
            "type": "array",
            "items": {
              "$ref": "#/components/schemas/Mission"
            },
            "nullable": true
          }
        },
        "additionalProperties": false
      },
      "Mission": {
        "type": "object",
        "properties": {
          "id": {
            "type": "string",
            "format": "uuid"
          },
          "careerPathId": {
            "type": "string",
            "format": "uuid"
          },
          "title": {
            "type": "string",
            "nullable": true
          },
          "description": {
            "type": "string",
            "nullable": true
          },
          "type": {
            "type": "string",
            "nullable": true
          },
          "difficulty": {
            "type": "integer",
            "format": "int32"
          },
          "estimatedMinutes": {
            "type": "integer",
            "format": "int32"
          },
          "xpReward": {
            "type": "integer",
            "format": "int32"
          }
        },
        "additionalProperties": false
      },
      "User": {
        "type": "object",
        "properties": {
          "id": {
            "type": "string",
            "format": "uuid"
          },
          "name": {
            "type": "string",
            "nullable": true
          },
          "email": {
            "type": "string",
            "nullable": true
          },
          "currentRole": {
            "type": "string",
            "nullable": true
          },
          "weeklyAvailableHours": {
            "type": "integer",
            "format": "int32"
          }
        },
        "additionalProperties": false
      },
      "UserMissionProgress": {
        "type": "object",
        "properties": {
          "id": {
            "type": "string",
            "format": "uuid"
          },
          "userId": {
            "type": "string",
            "format": "uuid"
          },
          "missionId": {
            "type": "string",
            "format": "uuid"
          },
          "status": {
            "type": "string",
            "nullable": true
          },
          "completedAt": {
            "type": "string",
            "format": "date-time",
            "nullable": true
          }
        },
        "additionalProperties": false
      }
    }
  }
}